arrapi/__init__.py
arrapi/exceptions.py
arrapi/apis/__init__.py
arrapi/apis/base.py
arrapi/apis/lidarr.py
arrapi/apis/radarr.py
arrapi/apis/readarr.py
arrapi/apis/sonarr.py
arrapi/objs/__init__.py
arrapi/objs/base.py
arrapi/objs/reload.py
arrapi/objs/simple.py
arrapi/raws/__init__.py
arrapi/raws/base.py
arrapi/raws/lidarr.py
arrapi/raws/radarr.py
arrapi/raws/readarr.py
arrapi/raws/sonarr.py
arrapi-1.4.14.dist-info/licenses/LICENSE
arrapi-1.4.14.dist-info/METADATA
arrapi-1.4.14.dist-info/WHEEL
arrapi-1.4.14.dist-info/top_level.txt
arrapi-1.4.14.dist-info/RECORD
