Metadata-Version: 2.4
Name: arrapi
Version: 1.4.14
Summary: Python wrapper for Radarr and Sonarr APIs:
Home-page: https://github.com/Kometa-Team/ArrAPI
Author: Nathan Taggart
Author-email: kometateam@proton.me
License: MIT License
Project-URL: Documentation, https://arrapi.kometa.wiki
Project-URL: Funding, https://github.com/sponsors/meisnate12
Project-URL: Source, https://github.com/Kometa-Team/ArrAPI
Project-URL: Issues, https://github.com/Kometa-Team/ArrAPI/issues
Keywords: arrapi,sonarr,radarr,arr,wrapper,api
Classifier: Development Status :: 5 - Production/Stable
Classifier: Intended Audience :: Developers
Classifier: Topic :: Software Development :: Libraries
Classifier: Programming Language :: Python
Classifier: Programming Language :: Python :: 3.8
Classifier: Programming Language :: Python :: 3.9
Classifier: Programming Language :: Python :: 3.10
Classifier: Programming Language :: Python :: 3.11
Classifier: Programming Language :: Python :: 3.12
Requires-Python: >=3.8
License-File: LICENSE
Requires-Dist: requests
Dynamic: author
Dynamic: author-email
Dynamic: classifier
Dynamic: description
Dynamic: home-page
Dynamic: keywords
Dynamic: license
Dynamic: license-file
Dynamic: project-url
Dynamic: requires-dist
Dynamic: requires-python
Dynamic: summary
